<?xml version="1.0" encoding="UTF-8"?>
<MetaDataObject xmlns="http://v8.1c.ru/8.3/MDClasses" xmlns:app="http://v8.1c.ru/8.2/managed-application/core" xmlns:cfg="http://v8.1c.ru/8.1/data/enterprise/current-config" xmlns:cmi="http://v8.1c.ru/8.2/managed-application/cmi" xmlns:ent="http://v8.1c.ru/8.1/data/enterprise" xmlns:lf="http://v8.1c.ru/8.2/managed-application/logform" xmlns:pal="http://v8.1c.ru/8.1/data/ui/colors/palette" xmlns:style="http://v8.1c.ru/8.1/data/ui/style" xmlns:sys="http://v8.1c.ru/8.1/data/ui/fonts/system" xmlns:v8="http://v8.1c.ru/8.1/data/core" xmlns:v8ui="http://v8.1c.ru/8.1/data/ui" xmlns:web="http://v8.1c.ru/8.1/data/ui/colors/web" xmlns:win="http://v8.1c.ru/8.1/data/ui/colors/windows" xmlns:xen="http://v8.1c.ru/8.3/xcf/enums" xmlns:xpr="http://v8.1c.ru/8.3/xcf/predef" xmlns:xr="http://v8.1c.ru/8.3/xcf/readable" xmlns:xs="http://www.w3.org/2001/XMLSchema" xmlns:xsi="http://www.w3.org/2001/XMLSchema-instance" version="2.21">
	<Task uuid="707a0f77-2d74-4d4f-b501-c3043d299313">
		<InternalInfo>
			<xr:GeneratedType name="TaskObject.Взаимодействие" category="Object">
				<xr:TypeId>8d726140-79b5-4b27-86be-859b3a6b685d</xr:TypeId>
				<xr:ValueId>62fdc095-97a6-4196-82d8-290859eb6c67</xr:ValueId>
			</xr:GeneratedType>
			<xr:GeneratedType name="TaskRef.Взаимодействие" category="Ref">
				<xr:TypeId>9aec764f-b59b-4273-bad8-318dedd496df</xr:TypeId>
				<xr:ValueId>44737c8c-d1f8-45e4-b921-bec74c8c35aa</xr:ValueId>
			</xr:GeneratedType>
			<xr:GeneratedType name="TaskSelection.Взаимодействие" category="Selection">
				<xr:TypeId>861b79ce-f002-40d8-96d9-249a3700e1e8</xr:TypeId>
				<xr:ValueId>c7a5bf4e-7cc3-43e5-ac45-ae4afc4b0d6f</xr:ValueId>
			</xr:GeneratedType>
			<xr:GeneratedType name="TaskList.Взаимодействие" category="List">
				<xr:TypeId>6d06963b-5bd3-40ac-9ea0-b588f300f91e</xr:TypeId>
				<xr:ValueId>8e006be4-9337-461e-9145-7ff47c343c4d</xr:ValueId>
			</xr:GeneratedType>
			<xr:GeneratedType name="TaskManager.Взаимодействие" category="Manager">
				<xr:TypeId>fdd3b106-ad8b-45fc-abee-91d0d374f33f</xr:TypeId>
				<xr:ValueId>3d92a885-2dc0-41f2-8548-27a1d956c878</xr:ValueId>
			</xr:GeneratedType>
		</InternalInfo>
		<Properties>
			<Name>Взаимодействие</Name>
			<Synonym>
				<v8:item>
					<v8:lang>ru</v8:lang>
					<v8:content>Взаимодействие</v8:content>
				</v8:item>
				<v8:item>
					<v8:lang>en</v8:lang>
					<v8:content>Interaction</v8:content>
				</v8:item>
			</Synonym>
			<Comment/>
			<UseStandardCommands>false</UseStandardCommands>
			<NumberType>String</NumberType>
			<NumberLength>12</NumberLength>
			<NumberAllowedLength>Fixed</NumberAllowedLength>
			<CheckUnique>true</CheckUnique>
			<Autonumbering>true</Autonumbering>
			<TaskNumberAutoPrefix>DontUse</TaskNumberAutoPrefix>
			<DescriptionLength>150</DescriptionLength>
			<Addressing/>
			<MainAddressingAttribute/>
			<CurrentPerformer/>
			<BasedOn/>
			<StandardAttributes>
				<xr:StandardAttribute name="Executed">
					<xr:LinkByType/>
					<xr:FillChecking>DontCheck</xr:FillChecking>
					<xr:MultiLine>false</xr:MultiLine>
					<xr:FillFromFillingValue>false</xr:FillFromFillingValue>
					<xr:CreateOnInput>Auto</xr:CreateOnInput>
					<xr:TypeReductionMode>TransformValues</xr:TypeReductionMode>
					<xr:MaxValue xsi:nil="true"/>
					<xr:ToolTip>
						<v8:item>
							<v8:lang>ru</v8:lang>
							<v8:content>Задача выполнена</v8:content>
						</v8:item>
						<v8:item>
							<v8:lang>en</v8:lang>
							<v8:content>Task is done</v8:content>
						</v8:item>
					</xr:ToolTip>
					<xr:ExtendedEdit>false</xr:ExtendedEdit>
					<xr:Format/>
					<xr:ChoiceForm/>
					<xr:QuickChoice>Auto</xr:QuickChoice>
					<xr:ChoiceHistoryOnInput>Auto</xr:ChoiceHistoryOnInput>
					<xr:EditFormat/>
					<xr:PasswordMode>false</xr:PasswordMode>
					<xr:DataHistory>Use</xr:DataHistory>
					<xr:MarkNegatives>false</xr:MarkNegatives>
					<xr:MinValue xsi:nil="true"/>
					<xr:Synonym>
						<v8:item>
							<v8:lang>ru</v8:lang>
							<v8:content>Выполнена</v8:content>
						</v8:item>
						<v8:item>
							<v8:lang>en</v8:lang>
							<v8:content>Done</v8:content>
						</v8:item>
					</xr:Synonym>
					<xr:Comment>Задача выполнена</xr:Comment>
					<xr:FullTextSearch>Use</xr:FullTextSearch>
					<xr:ChoiceParameterLinks/>
					<xr:FillValue xsi:type="xs:boolean">false</xr:FillValue>
					<xr:Mask/>
					<xr:ChoiceParameters/>
				</xr:StandardAttribute>
				<xr:StandardAttribute name="Description">
					<xr:LinkByType/>
					<xr:FillChecking>ShowError</xr:FillChecking>
					<xr:MultiLine>false</xr:MultiLine>
					<xr:FillFromFillingValue>false</xr:FillFromFillingValue>
					<xr:CreateOnInput>Auto</xr:CreateOnInput>
					<xr:TypeReductionMode>TransformValues</xr:TypeReductionMode>
					<xr:MaxValue xsi:nil="true"/>
					<xr:ToolTip>
						<v8:item>
							<v8:lang>ru</v8:lang>
							<v8:content>Краткое описание задачи</v8:content>
						</v8:item>
						<v8:item>
							<v8:lang>en</v8:lang>
							<v8:content>Short description tasks</v8:content>
						</v8:item>
					</xr:ToolTip>
					<xr:ExtendedEdit>false</xr:ExtendedEdit>
					<xr:Format/>
					<xr:ChoiceForm/>
					<xr:QuickChoice>Auto</xr:QuickChoice>
					<xr:ChoiceHistoryOnInput>Auto</xr:ChoiceHistoryOnInput>
					<xr:EditFormat/>
					<xr:PasswordMode>false</xr:PasswordMode>
					<xr:DataHistory>Use</xr:DataHistory>
					<xr:MarkNegatives>false</xr:MarkNegatives>
					<xr:MinValue xsi:nil="true"/>
					<xr:Synonym>
						<v8:item>
							<v8:lang>ru</v8:lang>
							<v8:content>Задача</v8:content>
						</v8:item>
						<v8:item>
							<v8:lang>en</v8:lang>
							<v8:content>Task</v8:content>
						</v8:item>
					</xr:Synonym>
					<xr:Comment>Краткое описание задачи</xr:Comment>
					<xr:FullTextSearch>Use</xr:FullTextSearch>
					<xr:ChoiceParameterLinks/>
					<xr:FillValue xsi:type="xs:string"/>
					<xr:Mask/>
					<xr:ChoiceParameters/>
				</xr:StandardAttribute>
				<xr:StandardAttribute name="RoutePoint">
					<xr:LinkByType/>
					<xr:FillChecking>DontCheck</xr:FillChecking>
					<xr:MultiLine>false</xr:MultiLine>
					<xr:FillFromFillingValue>false</xr:FillFromFillingValue>
					<xr:CreateOnInput>Auto</xr:CreateOnInput>
					<xr:TypeReductionMode>TransformValues</xr:TypeReductionMode>
					<xr:MaxValue xsi:nil="true"/>
					<xr:ToolTip/>
					<xr:ExtendedEdit>false</xr:ExtendedEdit>
					<xr:Format/>
					<xr:ChoiceForm/>
					<xr:QuickChoice>Auto</xr:QuickChoice>
					<xr:ChoiceHistoryOnInput>Auto</xr:ChoiceHistoryOnInput>
					<xr:EditFormat/>
					<xr:PasswordMode>false</xr:PasswordMode>
					<xr:DataHistory>Use</xr:DataHistory>
					<xr:MarkNegatives>false</xr:MarkNegatives>
					<xr:MinValue xsi:nil="true"/>
					<xr:Synonym/>
					<xr:Comment/>
					<xr:FullTextSearch>Use</xr:FullTextSearch>
					<xr:ChoiceParameterLinks/>
					<xr:FillValue xsi:type="xr:DesignTimeRef">1a8d6d2b-d737-4dd7-b1d8-deb2955d2feb.00000000-0000-0000-0000-000000000000</xr:FillValue>
					<xr:Mask/>
					<xr:ChoiceParameters/>
				</xr:StandardAttribute>
				<xr:StandardAttribute name="BusinessProcess">
					<xr:LinkByType/>
					<xr:FillChecking>DontCheck</xr:FillChecking>
					<xr:MultiLine>false</xr:MultiLine>
					<xr:FillFromFillingValue>false</xr:FillFromFillingValue>
					<xr:CreateOnInput>Auto</xr:CreateOnInput>
					<xr:TypeReductionMode>TransformValues</xr:TypeReductionMode>
					<xr:MaxValue xsi:nil="true"/>
					<xr:ToolTip/>
					<xr:ExtendedEdit>false</xr:ExtendedEdit>
					<xr:Format/>
					<xr:ChoiceForm/>
					<xr:QuickChoice>Auto</xr:QuickChoice>
					<xr:ChoiceHistoryOnInput>Auto</xr:ChoiceHistoryOnInput>
					<xr:EditFormat/>
					<xr:PasswordMode>false</xr:PasswordMode>
					<xr:DataHistory>Use</xr:DataHistory>
					<xr:MarkNegatives>false</xr:MarkNegatives>
					<xr:MinValue xsi:nil="true"/>
					<xr:Synonym/>
					<xr:Comment/>
					<xr:FullTextSearch>Use</xr:FullTextSearch>
					<xr:ChoiceParameterLinks/>
					<xr:FillValue xsi:type="xr:DesignTimeRef">ee2c7bb4-7e27-4297-ade4-0494e07c2147.00000000-0000-0000-0000-000000000000</xr:FillValue>
					<xr:Mask/>
					<xr:ChoiceParameters/>
				</xr:StandardAttribute>
				<xr:StandardAttribute name="Ref">
					<xr:LinkByType/>
					<xr:FillChecking>DontCheck</xr:FillChecking>
					<xr:MultiLine>false</xr:MultiLine>
					<xr:FillFromFillingValue>false</xr:FillFromFillingValue>
					<xr:CreateOnInput>Auto</xr:CreateOnInput>
					<xr:TypeReductionMode>TransformValues</xr:TypeReductionMode>
					<xr:MaxValue xsi:nil="true"/>
					<xr:ToolTip/>
					<xr:ExtendedEdit>false</xr:ExtendedEdit>
					<xr:Format/>
					<xr:ChoiceForm/>
					<xr:QuickChoice>Auto</xr:QuickChoice>
					<xr:ChoiceHistoryOnInput>Auto</xr:ChoiceHistoryOnInput>
					<xr:EditFormat/>
					<xr:PasswordMode>false</xr:PasswordMode>
					<xr:DataHistory>Use</xr:DataHistory>
					<xr:MarkNegatives>false</xr:MarkNegatives>
					<xr:MinValue xsi:nil="true"/>
					<xr:Synonym/>
					<xr:Comment/>
					<xr:FullTextSearch>Use</xr:FullTextSearch>
					<xr:ChoiceParameterLinks/>
					<xr:FillValue xsi:nil="true"/>
					<xr:Mask/>
					<xr:ChoiceParameters/>
				</xr:StandardAttribute>
				<xr:StandardAttribute name="DeletionMark">
					<xr:LinkByType/>
					<xr:FillChecking>DontCheck</xr:FillChecking>
					<xr:MultiLine>false</xr:MultiLine>
					<xr:FillFromFillingValue>false</xr:FillFromFillingValue>
					<xr:CreateOnInput>Auto</xr:CreateOnInput>
					<xr:TypeReductionMode>TransformValues</xr:TypeReductionMode>
					<xr:MaxValue xsi:nil="true"/>
					<xr:ToolTip/>
					<xr:ExtendedEdit>false</xr:ExtendedEdit>
					<xr:Format/>
					<xr:ChoiceForm/>
					<xr:QuickChoice>Auto</xr:QuickChoice>
					<xr:ChoiceHistoryOnInput>Auto</xr:ChoiceHistoryOnInput>
					<xr:EditFormat/>
					<xr:PasswordMode>false</xr:PasswordMode>
					<xr:DataHistory>Use</xr:DataHistory>
					<xr:MarkNegatives>false</xr:MarkNegatives>
					<xr:MinValue xsi:nil="true"/>
					<xr:Synonym/>
					<xr:Comment/>
					<xr:FullTextSearch>Use</xr:FullTextSearch>
					<xr:ChoiceParameterLinks/>
					<xr:FillValue xsi:type="xs:boolean">false</xr:FillValue>
					<xr:Mask/>
					<xr:ChoiceParameters/>
				</xr:StandardAttribute>
				<xr:StandardAttribute name="Date">
					<xr:LinkByType/>
					<xr:FillChecking>DontCheck</xr:FillChecking>
					<xr:MultiLine>false</xr:MultiLine>
					<xr:FillFromFillingValue>false</xr:FillFromFillingValue>
					<xr:CreateOnInput>Auto</xr:CreateOnInput>
					<xr:TypeReductionMode>TransformValues</xr:TypeReductionMode>
					<xr:MaxValue xsi:nil="true"/>
					<xr:ToolTip>
						<v8:item>
							<v8:lang>ru</v8:lang>
							<v8:content>Дата создания задачи</v8:content>
						</v8:item>
						<v8:item>
							<v8:lang>en</v8:lang>
							<v8:content>Date create tasks</v8:content>
						</v8:item>
					</xr:ToolTip>
					<xr:ExtendedEdit>false</xr:ExtendedEdit>
					<xr:Format/>
					<xr:ChoiceForm/>
					<xr:QuickChoice>Auto</xr:QuickChoice>
					<xr:ChoiceHistoryOnInput>Auto</xr:ChoiceHistoryOnInput>
					<xr:EditFormat/>
					<xr:PasswordMode>false</xr:PasswordMode>
					<xr:DataHistory>Use</xr:DataHistory>
					<xr:MarkNegatives>false</xr:MarkNegatives>
					<xr:MinValue xsi:nil="true"/>
					<xr:Synonym>
						<v8:item>
							<v8:lang>ru</v8:lang>
							<v8:content>Создана</v8:content>
						</v8:item>
						<v8:item>
							<v8:lang>en</v8:lang>
							<v8:content>Created</v8:content>
						</v8:item>
					</xr:Synonym>
					<xr:Comment>Дата создания задачи</xr:Comment>
					<xr:FullTextSearch>Use</xr:FullTextSearch>
					<xr:ChoiceParameterLinks/>
					<xr:FillValue xsi:type="xs:dateTime">0001-01-01T00:00:00</xr:FillValue>
					<xr:Mask/>
					<xr:ChoiceParameters/>
				</xr:StandardAttribute>
				<xr:StandardAttribute name="Number">
					<xr:LinkByType/>
					<xr:FillChecking>DontCheck</xr:FillChecking>
					<xr:MultiLine>false</xr:MultiLine>
					<xr:FillFromFillingValue>false</xr:FillFromFillingValue>
					<xr:CreateOnInput>Auto</xr:CreateOnInput>
					<xr:TypeReductionMode>TransformValues</xr:TypeReductionMode>
					<xr:MaxValue xsi:nil="true"/>
					<xr:ToolTip/>
					<xr:ExtendedEdit>false</xr:ExtendedEdit>
					<xr:Format/>
					<xr:ChoiceForm/>
					<xr:QuickChoice>Auto</xr:QuickChoice>
					<xr:ChoiceHistoryOnInput>Auto</xr:ChoiceHistoryOnInput>
					<xr:EditFormat/>
					<xr:PasswordMode>false</xr:PasswordMode>
					<xr:DataHistory>Use</xr:DataHistory>
					<xr:MarkNegatives>false</xr:MarkNegatives>
					<xr:MinValue xsi:nil="true"/>
					<xr:Synonym/>
					<xr:Comment/>
					<xr:FullTextSearch>Use</xr:FullTextSearch>
					<xr:ChoiceParameterLinks/>
					<xr:FillValue xsi:type="xs:string">            </xr:FillValue>
					<xr:Mask/>
					<xr:ChoiceParameters/>
				</xr:StandardAttribute>
			</StandardAttributes>
			<Characteristics/>
			<DefaultPresentation>AsDescription</DefaultPresentation>
			<EditType>InDialog</EditType>
			<InputByString>
				<xr:Field>Task.Взаимодействие.StandardAttribute.Description</xr:Field>
				<xr:Field>Task.Взаимодействие.StandardAttribute.Number</xr:Field>
			</InputByString>
			<SearchStringModeOnInputByString>Begin</SearchStringModeOnInputByString>
			<FullTextSearchOnInputByString>DontUse</FullTextSearchOnInputByString>
			<ChoiceDataGetModeOnInputByString>Directly</ChoiceDataGetModeOnInputByString>
			<CreateOnInput>DontUse</CreateOnInput>
			<DefaultObjectForm>Task.Взаимодействие.Form.ФормаЗадачи</DefaultObjectForm>
			<DefaultListForm>Task.Взаимодействие.Form.ФормаСпискаНовая</DefaultListForm>
			<DefaultChoiceForm/>
			<AuxiliaryObjectForm/>
			<AuxiliaryListForm/>
			<AuxiliaryChoiceForm/>
			<ChoiceHistoryOnInput>Auto</ChoiceHistoryOnInput>
			<IncludeHelpInContents>true</IncludeHelpInContents>
			<DataLockFields/>
			<DataLockControlMode>Automatic</DataLockControlMode>
			<FullTextSearch>Use</FullTextSearch>
			<ObjectPresentation/>
			<ExtendedObjectPresentation/>
			<ListPresentation/>
			<ExtendedListPresentation/>
			<Explanation/>
			<DataHistory>DontUse</DataHistory>
			<UpdateDataHistoryImmediatelyAfterWrite>false</UpdateDataHistoryImmediatelyAfterWrite>
			<ExecuteAfterWriteDataHistoryVersionProcessing>false</ExecuteAfterWriteDataHistoryVersionProcessing>
		</Properties>
		<ChildObjects>
			<Attribute uuid="e28de250-cbd1-4717-9b34-168226b91793">
				<Properties>
					<Name>СтруктурнаяЕдиница</Name>
					<Synonym>
						<v8:item>
							<v8:lang>ru</v8:lang>
							<v8:content>Структурная единица</v8:content>
						</v8:item>
						<v8:item>
							<v8:lang>en</v8:lang>
							<v8:content>Structural unit</v8:content>
						</v8:item>
					</Synonym>
					<Comment/>
					<Type>
						<v8:Type>cfg:CatalogRef.СтруктурныеЕдиницы</v8:Type>
					</Type>
					<PasswordMode>false</PasswordMode>
					<Format/>
					<EditFormat/>
					<ToolTip/>
					<MarkNegatives>false</MarkNegatives>
					<Mask/>
					<MultiLine>false</MultiLine>
					<ExtendedEdit>false</ExtendedEdit>
					<MinValue xsi:nil="true"/>
					<MaxValue xsi:nil="true"/>
					<FillFromFillingValue>false</FillFromFillingValue>
					<FillValue xsi:nil="true"/>
					<FillChecking>DontCheck</FillChecking>
					<ChoiceFoldersAndItems>Items</ChoiceFoldersAndItems>
					<ChoiceParameterLinks/>
					<ChoiceParameters/>
					<QuickChoice>Auto</QuickChoice>
					<CreateOnInput>Auto</CreateOnInput>
					<ChoiceForm/>
					<LinkByType/>
					<ChoiceHistoryOnInput>Auto</ChoiceHistoryOnInput>
					<Indexing>Index</Indexing>
					<FullTextSearch>Use</FullTextSearch>
					<DataHistory>Use</DataHistory>
				</Properties>
			</Attribute>
			<Attribute uuid="1bac08f6-d762-4530-bf2b-9f5510fb8063">
				<Properties>
					<Name>ТриггерноеСобытие</Name>
					<Synonym>
						<v8:item>
							<v8:lang>ru</v8:lang>
							<v8:content>Триггерное событие</v8:content>
						</v8:item>
						<v8:item>
							<v8:lang>en</v8:lang>
							<v8:content>Trigger event</v8:content>
						</v8:item>
					</Synonym>
					<Comment/>
					<Type>
						<v8:Type>cfg:CatalogRef.ТриггерныеСобытия</v8:Type>
					</Type>
					<PasswordMode>false</PasswordMode>
					<Format/>
					<EditFormat/>
					<ToolTip/>
					<MarkNegatives>false</MarkNegatives>
					<Mask/>
					<MultiLine>false</MultiLine>
					<ExtendedEdit>false</ExtendedEdit>
					<MinValue xsi:nil="true"/>
					<MaxValue xsi:nil="true"/>
					<FillFromFillingValue>false</FillFromFillingValue>
					<FillValue xsi:nil="true"/>
					<FillChecking>DontCheck</FillChecking>
					<ChoiceFoldersAndItems>Items</ChoiceFoldersAndItems>
					<ChoiceParameterLinks/>
					<ChoiceParameters/>
					<QuickChoice>Auto</QuickChoice>
					<CreateOnInput>Auto</CreateOnInput>
					<ChoiceForm/>
					<LinkByType/>
					<ChoiceHistoryOnInput>Auto</ChoiceHistoryOnInput>
					<Indexing>Index</Indexing>
					<FullTextSearch>Use</FullTextSearch>
					<DataHistory>Use</DataHistory>
				</Properties>
			</Attribute>
			<Attribute uuid="15246a8a-8667-462e-abc7-489e0bccecba">
				<Properties>
					<Name>Контрагент</Name>
					<Synonym>
						<v8:item>
							<v8:lang>ru</v8:lang>
							<v8:content>Контрагент</v8:content>
						</v8:item>
						<v8:item>
							<v8:lang>en</v8:lang>
							<v8:content>Counterparty</v8:content>
						</v8:item>
					</Synonym>
					<Comment/>
					<Type>
						<v8:Type>cfg:CatalogRef.Контрагенты</v8:Type>
					</Type>
					<PasswordMode>false</PasswordMode>
					<Format/>
					<EditFormat/>
					<ToolTip/>
					<MarkNegatives>false</MarkNegatives>
					<Mask/>
					<MultiLine>false</MultiLine>
					<ExtendedEdit>false</ExtendedEdit>
					<MinValue xsi:nil="true"/>
					<MaxValue xsi:nil="true"/>
					<FillFromFillingValue>false</FillFromFillingValue>
					<FillValue xsi:nil="true"/>
					<FillChecking>DontCheck</FillChecking>
					<ChoiceFoldersAndItems>Items</ChoiceFoldersAndItems>
					<ChoiceParameterLinks/>
					<ChoiceParameters/>
					<QuickChoice>Auto</QuickChoice>
					<CreateOnInput>Auto</CreateOnInput>
					<ChoiceForm/>
					<LinkByType/>
					<ChoiceHistoryOnInput>Auto</ChoiceHistoryOnInput>
					<Indexing>Index</Indexing>
					<FullTextSearch>Use</FullTextSearch>
					<DataHistory>Use</DataHistory>
				</Properties>
			</Attribute>
			<Attribute uuid="1017ac60-4b64-40eb-83dd-985e95ad097e">
				<Properties>
					<Name>ЗадачаТема</Name>
					<Synonym>
						<v8:item>
							<v8:lang>ru</v8:lang>
							<v8:content>Задача тема</v8:content>
						</v8:item>
						<v8:item>
							<v8:lang>en</v8:lang>
							<v8:content>Task topic</v8:content>
						</v8:item>
					</Synonym>
					<Comment>Содержание задачи</Comment>
					<Type>
						<v8:Type>xs:string</v8:Type>
						<v8:StringQualifiers>
							<v8:Length>1024</v8:Length>
							<v8:AllowedLength>Variable</v8:AllowedLength>
						</v8:StringQualifiers>
					</Type>
					<PasswordMode>false</PasswordMode>
					<Format/>
					<EditFormat/>
					<ToolTip>
						<v8:item>
							<v8:lang>ru</v8:lang>
							<v8:content>Содержание задачи.</v8:content>
						</v8:item>
						<v8:item>
							<v8:lang>en</v8:lang>
							<v8:content>Content tasks.</v8:content>
						</v8:item>
					</ToolTip>
					<MarkNegatives>false</MarkNegatives>
					<Mask/>
					<MultiLine>false</MultiLine>
					<ExtendedEdit>false</ExtendedEdit>
					<MinValue xsi:nil="true"/>
					<MaxValue xsi:nil="true"/>
					<FillFromFillingValue>false</FillFromFillingValue>
					<FillValue xsi:type="xs:string"/>
					<FillChecking>ShowError</FillChecking>
					<ChoiceFoldersAndItems>Items</ChoiceFoldersAndItems>
					<ChoiceParameterLinks/>
					<ChoiceParameters/>
					<QuickChoice>Auto</QuickChoice>
					<CreateOnInput>Auto</CreateOnInput>
					<ChoiceForm/>
					<LinkByType/>
					<ChoiceHistoryOnInput>Auto</ChoiceHistoryOnInput>
					<Indexing>DontIndex</Indexing>
					<FullTextSearch>Use</FullTextSearch>
					<DataHistory>Use</DataHistory>
				</Properties>
			</Attribute>
			<Attribute uuid="e7ab958e-2bf2-446a-badc-329b57abf86e">
				<Properties>
					<Name>ЗадачаПредмет</Name>
					<Synonym>
						<v8:item>
							<v8:lang>ru</v8:lang>
							<v8:content>Задача предмет</v8:content>
						</v8:item>
						<v8:item>
							<v8:lang>en</v8:lang>
							<v8:content>Task subject</v8:content>
						</v8:item>
					</Synonym>
					<Comment>Предмет задачи</Comment>
					<Type>
						<v8:Type>cfg:DocumentRef.Реализация</v8:Type>
						<v8:Type>cfg:CatalogRef.Заявки</v8:Type>
						<v8:Type>cfg:DocumentRef.ПланЛечения</v8:Type>
						<v8:Type>cfg:DocumentRef.Прием</v8:Type>
					</Type>
					<PasswordMode>false</PasswordMode>
					<Format/>
					<EditFormat/>
					<ToolTip>
						<v8:item>
							<v8:lang>ru</v8:lang>
							<v8:content>Объект информационной базы, по поводу которого была введена задача</v8:content>
						</v8:item>
						<v8:item>
							<v8:lang>en</v8:lang>
							<v8:content>AnObject informational databases about which the task was entered</v8:content>
						</v8:item>
					</ToolTip>
					<MarkNegatives>false</MarkNegatives>
					<Mask/>
					<MultiLine>false</MultiLine>
					<ExtendedEdit>false</ExtendedEdit>
					<MinValue xsi:nil="true"/>
					<MaxValue xsi:nil="true"/>
					<FillFromFillingValue>true</FillFromFillingValue>
					<FillValue xsi:type="xr:DesignTimeRef">Catalog.Контрагенты.EmptyRef</FillValue>
					<FillChecking>DontCheck</FillChecking>
					<ChoiceFoldersAndItems>Items</ChoiceFoldersAndItems>
					<ChoiceParameterLinks/>
					<ChoiceParameters/>
					<QuickChoice>Auto</QuickChoice>
					<CreateOnInput>Auto</CreateOnInput>
					<ChoiceForm/>
					<LinkByType/>
					<ChoiceHistoryOnInput>Auto</ChoiceHistoryOnInput>
					<Indexing>Index</Indexing>
					<FullTextSearch>Use</FullTextSearch>
					<DataHistory>Use</DataHistory>
				</Properties>
			</Attribute>
			<Attribute uuid="781c1f02-3df7-4932-b407-e16e37efdcef">
				<Properties>
					<Name>ЗадачаОписание</Name>
					<Synonym>
						<v8:item>
							<v8:lang>ru</v8:lang>
							<v8:content>Задача описание</v8:content>
						</v8:item>
						<v8:item>
							<v8:lang>en</v8:lang>
							<v8:content>Task description</v8:content>
						</v8:item>
					</Synonym>
					<Comment>Подробное описание задачи</Comment>
					<Type>
						<v8:Type>xs:string</v8:Type>
						<v8:StringQualifiers>
							<v8:Length>0</v8:Length>
							<v8:AllowedLength>Variable</v8:AllowedLength>
						</v8:StringQualifiers>
					</Type>
					<PasswordMode>false</PasswordMode>
					<Format/>
					<EditFormat/>
					<ToolTip>
						<v8:item>
							<v8:lang>ru</v8:lang>
							<v8:content>Подробное описание задачи.</v8:content>
						</v8:item>
						<v8:item>
							<v8:lang>en</v8:lang>
							<v8:content>Detailed description tasks.</v8:content>
						</v8:item>
					</ToolTip>
					<MarkNegatives>false</MarkNegatives>
					<Mask/>
					<MultiLine>true</MultiLine>
					<ExtendedEdit>true</ExtendedEdit>
					<MinValue xsi:nil="true"/>
					<MaxValue xsi:nil="true"/>
					<FillFromFillingValue>true</FillFromFillingValue>
					<FillValue xsi:type="xs:string"/>
					<FillChecking>DontCheck</FillChecking>
					<ChoiceFoldersAndItems>Items</ChoiceFoldersAndItems>
					<ChoiceParameterLinks/>
					<ChoiceParameters/>
					<QuickChoice>Auto</QuickChoice>
					<CreateOnInput>Auto</CreateOnInput>
					<ChoiceForm/>
					<LinkByType/>
					<ChoiceHistoryOnInput>Auto</ChoiceHistoryOnInput>
					<Indexing>DontIndex</Indexing>
					<FullTextSearch>Use</FullTextSearch>
					<DataHistory>Use</DataHistory>
				</Properties>
			</Attribute>
			<Attribute uuid="008e83a1-85fe-4199-bc5a-45b71185ad1a">
				<Properties>
					<Name>ЗадачаАвтор</Name>
					<Synonym>
						<v8:item>
							<v8:lang>ru</v8:lang>
							<v8:content>Задача автор</v8:content>
						</v8:item>
						<v8:item>
							<v8:lang>en</v8:lang>
							<v8:content>Task author</v8:content>
						</v8:item>
					</Synonym>
					<Comment>Автор бизнес-процесса, который сформировал задачу</Comment>
					<Type>
						<v8:Type>cfg:CatalogRef.Сотрудники</v8:Type>
					</Type>
					<PasswordMode>false</PasswordMode>
					<Format/>
					<EditFormat/>
					<ToolTip>
						<v8:item>
							<v8:lang>ru</v8:lang>
							<v8:content>Автор задачи</v8:content>
						</v8:item>
						<v8:item>
							<v8:lang>en</v8:lang>
							<v8:content>Author task</v8:content>
						</v8:item>
					</ToolTip>
					<MarkNegatives>false</MarkNegatives>
					<Mask/>
					<MultiLine>false</MultiLine>
					<ExtendedEdit>false</ExtendedEdit>
					<MinValue xsi:nil="true"/>
					<MaxValue xsi:nil="true"/>
					<FillFromFillingValue>false</FillFromFillingValue>
					<FillValue xsi:type="xr:DesignTimeRef">Catalog.Пользователи.EmptyRef</FillValue>
					<FillChecking>DontCheck</FillChecking>
					<ChoiceFoldersAndItems>Items</ChoiceFoldersAndItems>
					<ChoiceParameterLinks/>
					<ChoiceParameters/>
					<QuickChoice>Auto</QuickChoice>
					<CreateOnInput>Auto</CreateOnInput>
					<ChoiceForm/>
					<LinkByType/>
					<ChoiceHistoryOnInput>Auto</ChoiceHistoryOnInput>
					<Indexing>Index</Indexing>
					<FullTextSearch>Use</FullTextSearch>
					<DataHistory>Use</DataHistory>
				</Properties>
			</Attribute>
			<Attribute uuid="a071abfb-dfd3-4619-a8e0-74b631b42461">
				<Properties>
					<Name>ЗадачаНазначеннаяДатаНачало</Name>
					<Synonym>
						<v8:item>
							<v8:lang>ru</v8:lang>
							<v8:content>Задача назначенная дата начало</v8:content>
						</v8:item>
						<v8:item>
							<v8:lang>en</v8:lang>
							<v8:content>Task specified date start</v8:content>
						</v8:item>
					</Synonym>
					<Comment/>
					<Type>
						<v8:Type>xs:dateTime</v8:Type>
						<v8:DateQualifiers>
							<v8:DateFractions>DateTime</v8:DateFractions>
						</v8:DateQualifiers>
					</Type>
					<PasswordMode>false</PasswordMode>
					<Format/>
					<EditFormat/>
					<ToolTip/>
					<MarkNegatives>false</MarkNegatives>
					<Mask/>
					<MultiLine>false</MultiLine>
					<ExtendedEdit>false</ExtendedEdit>
					<MinValue xsi:nil="true"/>
					<MaxValue xsi:nil="true"/>
					<FillFromFillingValue>false</FillFromFillingValue>
					<FillValue xsi:nil="true"/>
					<FillChecking>DontCheck</FillChecking>
					<ChoiceFoldersAndItems>Items</ChoiceFoldersAndItems>
					<ChoiceParameterLinks/>
					<ChoiceParameters/>
					<QuickChoice>Auto</QuickChoice>
					<CreateOnInput>Auto</CreateOnInput>
					<ChoiceForm/>
					<LinkByType/>
					<ChoiceHistoryOnInput>Auto</ChoiceHistoryOnInput>
					<Indexing>Index</Indexing>
					<FullTextSearch>Use</FullTextSearch>
					<DataHistory>Use</DataHistory>
				</Properties>
			</Attribute>
			<Attribute uuid="a9f78e3c-88be-4ee4-9b20-42da6bcf5d76">
				<Properties>
					<Name>ЗадачаНазначеннаяДата</Name>
					<Synonym>
						<v8:item>
							<v8:lang>ru</v8:lang>
							<v8:content>Задача назначенная дата</v8:content>
						</v8:item>
						<v8:item>
							<v8:lang>en</v8:lang>
							<v8:content>Task designated date</v8:content>
						</v8:item>
					</Synonym>
					<Comment/>
					<Type>
						<v8:Type>xs:dateTime</v8:Type>
						<v8:DateQualifiers>
							<v8:DateFractions>DateTime</v8:DateFractions>
						</v8:DateQualifiers>
					</Type>
					<PasswordMode>false</PasswordMode>
					<Format/>
					<EditFormat/>
					<ToolTip/>
					<MarkNegatives>false</MarkNegatives>
					<Mask/>
					<MultiLine>false</MultiLine>
					<ExtendedEdit>false</ExtendedEdit>
					<MinValue xsi:nil="true"/>
					<MaxValue xsi:nil="true"/>
					<FillFromFillingValue>false</FillFromFillingValue>
					<FillValue xsi:nil="true"/>
					<FillChecking>DontCheck</FillChecking>
					<ChoiceFoldersAndItems>Items</ChoiceFoldersAndItems>
					<ChoiceParameterLinks/>
					<ChoiceParameters/>
					<QuickChoice>Auto</QuickChoice>
					<CreateOnInput>Auto</CreateOnInput>
					<ChoiceForm/>
					<LinkByType/>
					<ChoiceHistoryOnInput>Auto</ChoiceHistoryOnInput>
					<Indexing>Index</Indexing>
					<FullTextSearch>Use</FullTextSearch>
					<DataHistory>Use</DataHistory>
				</Properties>
			</Attribute>
			<Attribute uuid="1c3c6e6a-037d-4de3-be1d-1e6b120d28a5">
				<Properties>
					<Name>ДатаИсполнения</Name>
					<Synonym>
						<v8:item>
							<v8:lang>ru</v8:lang>
							<v8:content>Дата выполнения</v8:content>
						</v8:item>
						<v8:item>
							<v8:lang>en</v8:lang>
							<v8:content>Execution date</v8:content>
						</v8:item>
					</Synonym>
					<Comment>Дата и время фактического выполнения задачи</Comment>
					<Type>
						<v8:Type>xs:dateTime</v8:Type>
						<v8:DateQualifiers>
							<v8:DateFractions>DateTime</v8:DateFractions>
						</v8:DateQualifiers>
					</Type>
					<PasswordMode>false</PasswordMode>
					<Format/>
					<EditFormat/>
					<ToolTip>
						<v8:item>
							<v8:lang>ru</v8:lang>
							<v8:content>Фактическая дата выполнения задачи</v8:content>
						</v8:item>
						<v8:item>
							<v8:lang>en</v8:lang>
							<v8:content>Actual date run tasks</v8:content>
						</v8:item>
					</ToolTip>
					<MarkNegatives>false</MarkNegatives>
					<Mask/>
					<MultiLine>false</MultiLine>
					<ExtendedEdit>false</ExtendedEdit>
					<MinValue xsi:nil="true"/>
					<MaxValue xsi:nil="true"/>
					<FillFromFillingValue>false</FillFromFillingValue>
					<FillValue xsi:type="xs:dateTime">0001-01-01T00:00:00</FillValue>
					<FillChecking>DontCheck</FillChecking>
					<ChoiceFoldersAndItems>Items</ChoiceFoldersAndItems>
					<ChoiceParameterLinks/>
					<ChoiceParameters/>
					<QuickChoice>Auto</QuickChoice>
					<CreateOnInput>Auto</CreateOnInput>
					<ChoiceForm/>
					<LinkByType/>
					<ChoiceHistoryOnInput>Auto</ChoiceHistoryOnInput>
					<Indexing>Index</Indexing>
					<FullTextSearch>Use</FullTextSearch>
					<DataHistory>Use</DataHistory>
				</Properties>
			</Attribute>
			<Attribute uuid="a38bc811-34d4-4679-aecd-70fc74e079f8">
				<Properties>
					<Name>ИсполнительФактический</Name>
					<Synonym>
						<v8:item>
							<v8:lang>ru</v8:lang>
							<v8:content>Исполнитель фактический</v8:content>
						</v8:item>
						<v8:item>
							<v8:lang>en</v8:lang>
							<v8:content>Actual perpetrator</v8:content>
						</v8:item>
					</Synonym>
					<Comment/>
					<Type>
						<v8:Type>cfg:CatalogRef.Сотрудники</v8:Type>
					</Type>
					<PasswordMode>false</PasswordMode>
					<Format/>
					<EditFormat/>
					<ToolTip/>
					<MarkNegatives>false</MarkNegatives>
					<Mask/>
					<MultiLine>false</MultiLine>
					<ExtendedEdit>false</ExtendedEdit>
					<MinValue xsi:nil="true"/>
					<MaxValue xsi:nil="true"/>
					<FillFromFillingValue>false</FillFromFillingValue>
					<FillValue xsi:nil="true"/>
					<FillChecking>DontCheck</FillChecking>
					<ChoiceFoldersAndItems>Items</ChoiceFoldersAndItems>
					<ChoiceParameterLinks/>
					<ChoiceParameters/>
					<QuickChoice>Auto</QuickChoice>
					<CreateOnInput>Auto</CreateOnInput>
					<ChoiceForm/>
					<LinkByType/>
					<ChoiceHistoryOnInput>Auto</ChoiceHistoryOnInput>
					<Indexing>Index</Indexing>
					<FullTextSearch>Use</FullTextSearch>
					<DataHistory>Use</DataHistory>
				</Properties>
			</Attribute>
			<Attribute uuid="47803ef4-cac5-4739-be17-2ba109c08a75">
				<Properties>
					<Name>ВидВзаимодействия</Name>
					<Synonym>
						<v8:item>
							<v8:lang>ru</v8:lang>
							<v8:content>Вид взаимодействия</v8:content>
						</v8:item>
						<v8:item>
							<v8:lang>en</v8:lang>
							<v8:content>Type of interaction</v8:content>
						</v8:item>
					</Synonym>
					<Comment/>
					<Type>
						<v8:Type>cfg:EnumRef.ВидыВзаимодействия</v8:Type>
					</Type>
					<PasswordMode>false</PasswordMode>
					<Format/>
					<EditFormat/>
					<ToolTip/>
					<MarkNegatives>false</MarkNegatives>
					<Mask/>
					<MultiLine>false</MultiLine>
					<ExtendedEdit>false</ExtendedEdit>
					<MinValue xsi:nil="true"/>
					<MaxValue xsi:nil="true"/>
					<FillFromFillingValue>false</FillFromFillingValue>
					<FillValue xsi:nil="true"/>
					<FillChecking>DontCheck</FillChecking>
					<ChoiceFoldersAndItems>Items</ChoiceFoldersAndItems>
					<ChoiceParameterLinks/>
					<ChoiceParameters/>
					<QuickChoice>Auto</QuickChoice>
					<CreateOnInput>Auto</CreateOnInput>
					<ChoiceForm/>
					<LinkByType/>
					<ChoiceHistoryOnInput>Auto</ChoiceHistoryOnInput>
					<Indexing>DontIndex</Indexing>
					<FullTextSearch>Use</FullTextSearch>
					<DataHistory>Use</DataHistory>
				</Properties>
			</Attribute>
			<Attribute uuid="ec30f8d7-d54c-4491-bc73-021c05395445">
				<Properties>
					<Name>ВидВзаимодействияСправочник</Name>
					<Synonym>
						<v8:item>
							<v8:lang>ru</v8:lang>
							<v8:content>Вид взаимодействия справочник</v8:content>
						</v8:item>
						<v8:item>
							<v8:lang>en</v8:lang>
							<v8:content>Type of cooperation catalog</v8:content>
						</v8:item>
					</Synonym>
					<Comment/>
					<Type>
						<v8:Type>cfg:CatalogRef.ВидыВзаимодействий</v8:Type>
					</Type>
					<PasswordMode>false</PasswordMode>
					<Format/>
					<EditFormat/>
					<ToolTip/>
					<MarkNegatives>false</MarkNegatives>
					<Mask/>
					<MultiLine>false</MultiLine>
					<ExtendedEdit>false</ExtendedEdit>
					<MinValue xsi:nil="true"/>
					<MaxValue xsi:nil="true"/>
					<FillFromFillingValue>false</FillFromFillingValue>
					<FillValue xsi:nil="true"/>
					<FillChecking>DontCheck</FillChecking>
					<ChoiceFoldersAndItems>Items</ChoiceFoldersAndItems>
					<ChoiceParameterLinks/>
					<ChoiceParameters/>
					<QuickChoice>Auto</QuickChoice>
					<CreateOnInput>Auto</CreateOnInput>
					<ChoiceForm/>
					<LinkByType/>
					<ChoiceHistoryOnInput>Auto</ChoiceHistoryOnInput>
					<Indexing>Index</Indexing>
					<FullTextSearch>Use</FullTextSearch>
					<DataHistory>Use</DataHistory>
				</Properties>
			</Attribute>
			<Attribute uuid="3a1061ad-de3b-4b40-adf5-f50700c46888">
				<Properties>
					<Name>ВзаимодействиеСостоялось</Name>
					<Synonym>
						<v8:item>
							<v8:lang>ru</v8:lang>
							<v8:content>Взаимодействие состоялось</v8:content>
						</v8:item>
						<v8:item>
							<v8:lang>en</v8:lang>
							<v8:content>The interaction took place</v8:content>
						</v8:item>
					</Synonym>
					<Comment/>
					<Type>
						<v8:Type>xs:boolean</v8:Type>
					</Type>
					<PasswordMode>false</PasswordMode>
					<Format/>
					<EditFormat/>
					<ToolTip/>
					<MarkNegatives>false</MarkNegatives>
					<Mask/>
					<MultiLine>false</MultiLine>
					<ExtendedEdit>false</ExtendedEdit>
					<MinValue xsi:nil="true"/>
					<MaxValue xsi:nil="true"/>
					<FillFromFillingValue>false</FillFromFillingValue>
					<FillValue xsi:nil="true"/>
					<FillChecking>DontCheck</FillChecking>
					<ChoiceFoldersAndItems>Items</ChoiceFoldersAndItems>
					<ChoiceParameterLinks/>
					<ChoiceParameters/>
					<QuickChoice>Auto</QuickChoice>
					<CreateOnInput>Auto</CreateOnInput>
					<ChoiceForm/>
					<LinkByType/>
					<ChoiceHistoryOnInput>Auto</ChoiceHistoryOnInput>
					<Indexing>DontIndex</Indexing>
					<FullTextSearch>Use</FullTextSearch>
					<DataHistory>Use</DataHistory>
				</Properties>
			</Attribute>
			<Attribute uuid="db9141ae-d202-4997-8247-3f2193ef7066">
				<Properties>
					<Name>НапоминаниеИспользовать</Name>
					<Synonym>
						<v8:item>
							<v8:lang>ru</v8:lang>
							<v8:content>Напоминание использовать</v8:content>
						</v8:item>
						<v8:item>
							<v8:lang>en</v8:lang>
							<v8:content>Reminder to use</v8:content>
						</v8:item>
					</Synonym>
					<Comment>Напоминать о задаче</Comment>
					<Type>
						<v8:Type>xs:boolean</v8:Type>
					</Type>
					<PasswordMode>false</PasswordMode>
					<Format/>
					<EditFormat/>
					<ToolTip>
						<v8:item>
							<v8:lang>ru</v8:lang>
							<v8:content>Флаг указывает о необходимости напоминать о задаче.</v8:content>
						</v8:item>
						<v8:item>
							<v8:lang>en</v8:lang>
							<v8:content>Flag indicates the need to remind about the task.</v8:content>
						</v8:item>
					</ToolTip>
					<MarkNegatives>false</MarkNegatives>
					<Mask/>
					<MultiLine>false</MultiLine>
					<ExtendedEdit>false</ExtendedEdit>
					<MinValue xsi:nil="true"/>
					<MaxValue xsi:nil="true"/>
					<FillFromFillingValue>false</FillFromFillingValue>
					<FillValue xsi:nil="true"/>
					<FillChecking>DontCheck</FillChecking>
					<ChoiceFoldersAndItems>Items</ChoiceFoldersAndItems>
					<ChoiceParameterLinks/>
					<ChoiceParameters/>
					<QuickChoice>Auto</QuickChoice>
					<CreateOnInput>Auto</CreateOnInput>
					<ChoiceForm/>
					<LinkByType/>
					<ChoiceHistoryOnInput>Auto</ChoiceHistoryOnInput>
					<Indexing>Index</Indexing>
					<FullTextSearch>Use</FullTextSearch>
					<DataHistory>Use</DataHistory>
				</Properties>
			</Attribute>
			<Attribute uuid="cbc0112c-d2fe-43b8-b1bd-78391a9164e3">
				<Properties>
					<Name>ВариантНапоминания</Name>
					<Synonym>
						<v8:item>
							<v8:lang>ru</v8:lang>
							<v8:content>Вариант напоминания</v8:content>
						</v8:item>
						<v8:item>
							<v8:lang>en</v8:lang>
							<v8:content>Option reminder</v8:content>
						</v8:item>
					</Synonym>
					<Comment/>
					<Type>
						<v8:Type>cfg:EnumRef.ВариантыНапоминаний</v8:Type>
					</Type>
					<PasswordMode>false</PasswordMode>
					<Format/>
					<EditFormat/>
					<ToolTip/>
					<MarkNegatives>false</MarkNegatives>
					<Mask/>
					<MultiLine>false</MultiLine>
					<ExtendedEdit>false</ExtendedEdit>
					<MinValue xsi:nil="true"/>
					<MaxValue xsi:nil="true"/>
					<FillFromFillingValue>false</FillFromFillingValue>
					<FillValue xsi:nil="true"/>
					<FillChecking>DontCheck</FillChecking>
					<ChoiceFoldersAndItems>Items</ChoiceFoldersAndItems>
					<ChoiceParameterLinks/>
					<ChoiceParameters/>
					<QuickChoice>Auto</QuickChoice>
					<CreateOnInput>Auto</CreateOnInput>
					<ChoiceForm/>
					<LinkByType/>
					<ChoiceHistoryOnInput>Auto</ChoiceHistoryOnInput>
					<Indexing>Index</Indexing>
					<FullTextSearch>Use</FullTextSearch>
					<DataHistory>Use</DataHistory>
				</Properties>
			</Attribute>
			<Attribute uuid="8efe6515-4232-43e5-a926-ca7e55ca5b33">
				<Properties>
					<Name>НапоминаниеДатаНачала</Name>
					<Synonym>
						<v8:item>
							<v8:lang>ru</v8:lang>
							<v8:content>Напоминание дата начала</v8:content>
						</v8:item>
						<v8:item>
							<v8:lang>en</v8:lang>
							<v8:content>Starting date reminder</v8:content>
						</v8:item>
					</Synonym>
					<Comment/>
					<Type>
						<v8:Type>xs:dateTime</v8:Type>
						<v8:DateQualifiers>
							<v8:DateFractions>DateTime</v8:DateFractions>
						</v8:DateQualifiers>
					</Type>
					<PasswordMode>false</PasswordMode>
					<Format/>
					<EditFormat/>
					<ToolTip/>
					<MarkNegatives>false</MarkNegatives>
					<Mask/>
					<MultiLine>false</MultiLine>
					<ExtendedEdit>false</ExtendedEdit>
					<MinValue xsi:nil="true"/>
					<MaxValue xsi:nil="true"/>
					<FillFromFillingValue>false</FillFromFillingValue>
					<FillValue xsi:nil="true"/>
					<FillChecking>DontCheck</FillChecking>
					<ChoiceFoldersAndItems>Items</ChoiceFoldersAndItems>
					<ChoiceParameterLinks/>
					<ChoiceParameters/>
					<QuickChoice>Auto</QuickChoice>
					<CreateOnInput>Auto</CreateOnInput>
					<ChoiceForm/>
					<LinkByType/>
					<ChoiceHistoryOnInput>Auto</ChoiceHistoryOnInput>
					<Indexing>Index</Indexing>
					<FullTextSearch>Use</FullTextSearch>
					<DataHistory>Use</DataHistory>
				</Properties>
			</Attribute>
			<Attribute uuid="f5c3a174-0941-42d9-a7cc-4e5e25516f9a">
				<Properties>
					<Name>КоличествоПереносов</Name>
					<Synonym>
						<v8:item>
							<v8:lang>ru</v8:lang>
							<v8:content>Количество переносов</v8:content>
						</v8:item>
						<v8:item>
							<v8:lang>en</v8:lang>
							<v8:content>Number of postponements</v8:content>
						</v8:item>
					</Synonym>
					<Comment/>
					<Type>
						<v8:Type>xs:decimal</v8:Type>
						<v8:NumberQualifiers>
							<v8:Digits>3</v8:Digits>
							<v8:FractionDigits>0</v8:FractionDigits>
							<v8:AllowedSign>Nonnegative</v8:AllowedSign>
						</v8:NumberQualifiers>
					</Type>
					<PasswordMode>false</PasswordMode>
					<Format/>
					<EditFormat/>
					<ToolTip/>
					<MarkNegatives>false</MarkNegatives>
					<Mask/>
					<MultiLine>false</MultiLine>
					<ExtendedEdit>false</ExtendedEdit>
					<MinValue xsi:nil="true"/>
					<MaxValue xsi:nil="true"/>
					<FillFromFillingValue>false</FillFromFillingValue>
					<FillValue xsi:nil="true"/>
					<FillChecking>DontCheck</FillChecking>
					<ChoiceFoldersAndItems>Items</ChoiceFoldersAndItems>
					<ChoiceParameterLinks/>
					<ChoiceParameters/>
					<QuickChoice>Auto</QuickChoice>
					<CreateOnInput>Auto</CreateOnInput>
					<ChoiceForm/>
					<LinkByType/>
					<ChoiceHistoryOnInput>Auto</ChoiceHistoryOnInput>
					<Indexing>DontIndex</Indexing>
					<FullTextSearch>Use</FullTextSearch>
					<DataHistory>Use</DataHistory>
				</Properties>
			</Attribute>
			<Attribute uuid="51301458-e3c2-44fe-be16-0b3513bebc11">
				<Properties>
					<Name>КодСинхронизации</Name>
					<Synonym>
						<v8:item>
							<v8:lang>ru</v8:lang>
							<v8:content>Код синхронизации</v8:content>
						</v8:item>
						<v8:item>
							<v8:lang>en</v8:lang>
							<v8:content>Synchronization code</v8:content>
						</v8:item>
					</Synonym>
					<Comment>Код синхронизации с ID загружаемой базы</Comment>
					<Type>
						<v8:Type>xs:string</v8:Type>
						<v8:StringQualifiers>
							<v8:Length>40</v8:Length>
							<v8:AllowedLength>Variable</v8:AllowedLength>
						</v8:StringQualifiers>
					</Type>
					<PasswordMode>false</PasswordMode>
					<Format/>
					<EditFormat/>
					<ToolTip/>
					<MarkNegatives>false</MarkNegatives>
					<Mask/>
					<MultiLine>false</MultiLine>
					<ExtendedEdit>false</ExtendedEdit>
					<MinValue xsi:nil="true"/>
					<MaxValue xsi:nil="true"/>
					<FillFromFillingValue>false</FillFromFillingValue>
					<FillValue xsi:nil="true"/>
					<FillChecking>DontCheck</FillChecking>
					<ChoiceFoldersAndItems>Items</ChoiceFoldersAndItems>
					<ChoiceParameterLinks/>
					<ChoiceParameters/>
					<QuickChoice>Auto</QuickChoice>
					<CreateOnInput>Auto</CreateOnInput>
					<ChoiceForm/>
					<LinkByType/>
					<ChoiceHistoryOnInput>Auto</ChoiceHistoryOnInput>
					<Indexing>Index</Indexing>
					<FullTextSearch>Use</FullTextSearch>
					<DataHistory>Use</DataHistory>
				</Properties>
			</Attribute>
			<Attribute uuid="b2581246-c539-44ea-9f3c-81557d7f075b">
				<Properties>
					<Name>ПрефиксСинхронизации</Name>
					<Synonym>
						<v8:item>
							<v8:lang>ru</v8:lang>
							<v8:content>Префикс синхронизации</v8:content>
						</v8:item>
					</Synonym>
					<Comment/>
					<Type>
						<v8:Type>xs:string</v8:Type>
						<v8:StringQualifiers>
							<v8:Length>5</v8:Length>
							<v8:AllowedLength>Variable</v8:AllowedLength>
						</v8:StringQualifiers>
					</Type>
					<PasswordMode>false</PasswordMode>
					<Format/>
					<EditFormat/>
					<ToolTip/>
					<MarkNegatives>false</MarkNegatives>
					<Mask/>
					<MultiLine>false</MultiLine>
					<ExtendedEdit>false</ExtendedEdit>
					<MinValue xsi:nil="true"/>
					<MaxValue xsi:nil="true"/>
					<FillFromFillingValue>false</FillFromFillingValue>
					<FillValue xsi:type="xs:string"/>
					<FillChecking>DontCheck</FillChecking>
					<ChoiceFoldersAndItems>Items</ChoiceFoldersAndItems>
					<ChoiceParameterLinks/>
					<ChoiceParameters/>
					<QuickChoice>Auto</QuickChoice>
					<CreateOnInput>Auto</CreateOnInput>
					<ChoiceForm/>
					<LinkByType/>
					<ChoiceHistoryOnInput>Auto</ChoiceHistoryOnInput>
					<Indexing>Index</Indexing>
					<FullTextSearch>Use</FullTextSearch>
					<DataHistory>Use</DataHistory>
				</Properties>
			</Attribute>
			<Attribute uuid="c0512f37-af1c-46c1-b480-a818e5156626">
				<Properties>
					<Name>ВзаимодействиеПредставление</Name>
					<Synonym>
						<v8:item>
							<v8:lang>ru</v8:lang>
							<v8:content>Взаимодействие представление</v8:content>
						</v8:item>
						<v8:item>
							<v8:lang>en</v8:lang>
							<v8:content>Interaction representation</v8:content>
						</v8:item>
					</Synonym>
					<Comment>Представление задачи</Comment>
					<Type>
						<v8:Type>xs:string</v8:Type>
						<v8:StringQualifiers>
							<v8:Length>0</v8:Length>
							<v8:AllowedLength>Variable</v8:AllowedLength>
						</v8:StringQualifiers>
					</Type>
					<PasswordMode>false</PasswordMode>
					<Format/>
					<EditFormat/>
					<ToolTip/>
					<MarkNegatives>false</MarkNegatives>
					<Mask/>
					<MultiLine>false</MultiLine>
					<ExtendedEdit>false</ExtendedEdit>
					<MinValue xsi:nil="true"/>
					<MaxValue xsi:nil="true"/>
					<FillFromFillingValue>false</FillFromFillingValue>
					<FillValue xsi:type="xs:string"/>
					<FillChecking>DontCheck</FillChecking>
					<ChoiceFoldersAndItems>Items</ChoiceFoldersAndItems>
					<ChoiceParameterLinks/>
					<ChoiceParameters/>
					<QuickChoice>Auto</QuickChoice>
					<CreateOnInput>Auto</CreateOnInput>
					<ChoiceForm/>
					<LinkByType/>
					<ChoiceHistoryOnInput>Auto</ChoiceHistoryOnInput>
					<Indexing>DontIndex</Indexing>
					<FullTextSearch>Use</FullTextSearch>
					<DataHistory>Use</DataHistory>
				</Properties>
			</Attribute>
			<Attribute uuid="66762a20-cf4d-466b-a57a-5683e846cc58">
				<Properties>
					<Name>Сделка</Name>
					<Synonym>
						<v8:item>
							<v8:lang>ru</v8:lang>
							<v8:content>Сделка</v8:content>
						</v8:item>
						<v8:item>
							<v8:lang>en</v8:lang>
							<v8:content>Deal</v8:content>
						</v8:item>
					</Synonym>
					<Comment/>
					<Type>
						<v8:Type>cfg:CatalogRef.Сделки</v8:Type>
					</Type>
					<PasswordMode>false</PasswordMode>
					<Format/>
					<EditFormat/>
					<ToolTip/>
					<MarkNegatives>false</MarkNegatives>
					<Mask/>
					<MultiLine>false</MultiLine>
					<ExtendedEdit>false</ExtendedEdit>
					<MinValue xsi:nil="true"/>
					<MaxValue xsi:nil="true"/>
					<FillFromFillingValue>false</FillFromFillingValue>
					<FillValue xsi:nil="true"/>
					<FillChecking>DontCheck</FillChecking>
					<ChoiceFoldersAndItems>Items</ChoiceFoldersAndItems>
					<ChoiceParameterLinks/>
					<ChoiceParameters/>
					<QuickChoice>Auto</QuickChoice>
					<CreateOnInput>Auto</CreateOnInput>
					<ChoiceForm/>
					<LinkByType/>
					<ChoiceHistoryOnInput>Auto</ChoiceHistoryOnInput>
					<Indexing>Index</Indexing>
					<FullTextSearch>Use</FullTextSearch>
					<DataHistory>Use</DataHistory>
				</Properties>
			</Attribute>
			<Form>ФормаЗадачи</Form>
			<Form>ФормаВыбораВремени</Form>
			<Form>ФормаВыбораИсполнителя</Form>
			<Form>ФормаНапоминания</Form>
			<Form>ФормаСписка</Form>
			<Form>ФормаСпискаНовая</Form>
			<Form>ФормаСпискаПерейти_Расширенная</Form>
			<Form>ФормаСпискаПерейти</Form>
			<Form>ФормаЗадачиБыстрая</Form>
			<Form>ФормаФильтры</Form>
			<Form>ФормаИзменить</Form>
			<AddressingAttribute uuid="62546f70-b7c4-45f0-a57e-658e6e875f9a">
				<Properties>
					<Name>Исполнитель</Name>
					<Synonym>
						<v8:item>
							<v8:lang>ru</v8:lang>
							<v8:content>Исполнитель</v8:content>
						</v8:item>
						<v8:item>
							<v8:lang>en</v8:lang>
							<v8:content>Perpetrator</v8:content>
						</v8:item>
					</Synonym>
					<Comment>Исполнитель</Comment>
					<Type>
						<v8:Type>cfg:CatalogRef.СегментыСотрудников</v8:Type>
						<v8:Type>cfg:CatalogRef.Заявки</v8:Type>
						<v8:Type>cfg:CatalogRef.Сотрудники</v8:Type>
					</Type>
					<PasswordMode>false</PasswordMode>
					<Format/>
					<EditFormat/>
					<ToolTip>
						<v8:item>
							<v8:lang>ru</v8:lang>
							<v8:content>Исполнитель, которому поручено выполнение задачи</v8:content>
						</v8:item>
						<v8:item>
							<v8:lang>en</v8:lang>
							<v8:content>Perpetrator tasked with performance tasks</v8:content>
						</v8:item>
					</ToolTip>
					<MarkNegatives>false</MarkNegatives>
					<Mask/>
					<MultiLine>false</MultiLine>
					<ExtendedEdit>false</ExtendedEdit>
					<MinValue xsi:nil="true"/>
					<MaxValue xsi:nil="true"/>
					<FillFromFillingValue>false</FillFromFillingValue>
					<FillValue xsi:type="xr:DesignTimeRef">Catalog.Пользователи.EmptyRef</FillValue>
					<FillChecking>DontCheck</FillChecking>
					<ChoiceFoldersAndItems>Items</ChoiceFoldersAndItems>
					<ChoiceParameterLinks/>
					<ChoiceParameters/>
					<QuickChoice>Auto</QuickChoice>
					<CreateOnInput>Auto</CreateOnInput>
					<ChoiceForm/>
					<LinkByType/>
					<ChoiceHistoryOnInput>Auto</ChoiceHistoryOnInput>
					<Indexing>Index</Indexing>
					<AddressingDimension/>
					<FullTextSearch>Use</FullTextSearch>
					<DataHistory>Use</DataHistory>
				</Properties>
			</AddressingAttribute>
			<Command uuid="8025c1d7-720d-4c47-a25d-7ead93642b81">
				<Properties>
					<Name>ЗадачиКлиента</Name>
					<Synonym>
						<v8:item>
							<v8:lang>ru</v8:lang>
							<v8:content>Задачи</v8:content>
						</v8:item>
						<v8:item>
							<v8:lang>en</v8:lang>
							<v8:content>Tasks</v8:content>
						</v8:item>
					</Synonym>
					<Comment/>
					<Group>FormNavigationPanelGoTo</Group>
					<CommandParameterType>
						<v8:Type>cfg:CatalogRef.Контрагенты</v8:Type>
					</CommandParameterType>
					<ParameterUseMode>Single</ParameterUseMode>
					<ModifiesData>false</ModifiesData>
					<Representation>Auto</Representation>
					<ToolTip>
						<v8:item>
							<v8:lang>ru</v8:lang>
							<v8:content>Показать задачи клиента</v8:content>
						</v8:item>
						<v8:item>
							<v8:lang>en</v8:lang>
							<v8:content>Show tasks client</v8:content>
						</v8:item>
					</ToolTip>
					<Picture/>
					<Shortcut/>
					<OnMainServerUnavalableBehavior>Auto</OnMainServerUnavalableBehavior>
				</Properties>
			</Command>
			<Command uuid="f37394b9-3ef0-4152-b0bf-cbc23d8f9aa8">
				<Properties>
					<Name>ЗадачиПользователей</Name>
					<Synonym>
						<v8:item>
							<v8:lang>ru</v8:lang>
							<v8:content>Задачи</v8:content>
						</v8:item>
						<v8:item>
							<v8:lang>en</v8:lang>
							<v8:content>Tasks</v8:content>
						</v8:item>
					</Synonym>
					<Comment/>
					<Group>NavigationPanelOrdinary</Group>
					<CommandParameterType/>
					<ParameterUseMode>Single</ParameterUseMode>
					<ModifiesData>false</ModifiesData>
					<Representation>Auto</Representation>
					<ToolTip>
						<v8:item>
							<v8:lang>ru</v8:lang>
							<v8:content>Просмотреть задачи пользователей</v8:content>
						</v8:item>
						<v8:item>
							<v8:lang>en</v8:lang>
							<v8:content>View tasks users</v8:content>
						</v8:item>
					</ToolTip>
					<Picture/>
					<Shortcut/>
					<OnMainServerUnavalableBehavior>Auto</OnMainServerUnavalableBehavior>
				</Properties>
			</Command>
			<Command uuid="2f919a8d-d627-4711-890c-f33df944a508">
				<Properties>
					<Name>ЗадачиБизнесПроцесса</Name>
					<Synonym>
						<v8:item>
							<v8:lang>ru</v8:lang>
							<v8:content>Задачи процесса</v8:content>
						</v8:item>
						<v8:item>
							<v8:lang>en</v8:lang>
							<v8:content>Tasks process</v8:content>
						</v8:item>
					</Synonym>
					<Comment/>
					<Group>FormNavigationPanelGoTo</Group>
					<CommandParameterType>
						<v8:Type>cfg:TaskRef.ЗадачаИсполнителя</v8:Type>
					</CommandParameterType>
					<ParameterUseMode>Single</ParameterUseMode>
					<ModifiesData>false</ModifiesData>
					<Representation>Auto</Representation>
					<ToolTip/>
					<Picture/>
					<Shortcut/>
					<OnMainServerUnavalableBehavior>Auto</OnMainServerUnavalableBehavior>
				</Properties>
			</Command>
		</ChildObjects>
	</Task>
</MetaDataObject>